MANIFEST.in
README.rst
setup.py
aliyun_python_sdk_democenter.egg-info/PKG-INFO
aliyun_python_sdk_democenter.egg-info/SOURCES.txt
aliyun_python_sdk_democenter.egg-info/dependency_links.txt
aliyun_python_sdk_democenter.egg-info/requires.txt
aliyun_python_sdk_democenter.egg-info/top_level.txt
aliyunsdkdemocenter/__init__.py
aliyunsdkdemocenter/endpoint.py
aliyunsdkdemocenter/request/__init__.py
aliyunsdkdemocenter/request/v20200121/CreateDemoAccessTokenRequest.py
aliyunsdkdemocenter/request/v20200121/DescribeDemoAccessTokenRequest.py
aliyunsdkdemocenter/request/v20200121/ExpireDemoAccessTokenRequest.py
aliyunsdkdemocenter/request/v20200121/GetDemoTrialAuthRequest.py
aliyunsdkdemocenter/request/v20200121/__init__.py